<?xml version='1.0' encoding='utf-8'?>
<annotation><filename>S0275</filename><size><width>512</width><height>512</height><depth>3</depth></size><object><name>Glabella</name><bndbox><xmin>318</xmin><ymin>136</ymin><xmax>382</xmax><ymax>200</ymax></bndbox></object><object><name>R3</name><bndbox><xmin>174</xmin><ymin>229</ymin><xmax>238</xmax><ymax>293</ymax></bndbox></object><object><name>Cervical point</name><bndbox><xmin>195</xmin><ymin>412</ymin><xmax>259</xmax><ymax>476</ymax></bndbox></object><object><name>Go-2 Ramus down</name><bndbox><xmin>138</xmin><ymin>238</ymin><xmax>202</xmax><ymax>302</ymax></bndbox></object><object><name>Nasion</name><bndbox><xmin>295</xmin><ymin>151</ymin><xmax>359</xmax><ymax>215</ymax></bndbox></object><object><name>Pogonion</name><bndbox><xmin>271</xmin><ymin>367</ymin><xmax>335</xmax><ymax>431</ymax></bndbox></object></annotation>