<?xml version='1.0' encoding='utf-8'?>
<annotation><filename>S0303</filename><size><width>512</width><height>512</height><depth>3</depth></size><object><name>Glabella</name><bndbox><xmin>430</xmin><ymin>143</ymin><xmax>494</xmax><ymax>207</ymax></bndbox></object><object><name>R3</name><bndbox><xmin>277</xmin><ymin>236</ymin><xmax>341</xmax><ymax>300</ymax></bndbox></object><object><name>Nasion</name><bndbox><xmin>406</xmin><ymin>161</ymin><xmax>470</xmax><ymax>225</ymax></bndbox></object></annotation>