<?xml version='1.0' encoding='utf-8'?>
<annotation><filename>S0491</filename><size><width>512</width><height>512</height><depth>3</depth></size><object><name>Glabella</name><bndbox><xmin>330</xmin><ymin>66</ymin><xmax>394</xmax><ymax>130</ymax></bndbox></object><object><name>R3</name><bndbox><xmin>186</xmin><ymin>207</ymin><xmax>250</xmax><ymax>271</ymax></bndbox></object><object><name>Nasion</name><bndbox><xmin>318</xmin><ymin>85</ymin><xmax>382</xmax><ymax>149</ymax></bndbox></object></annotation>